{
  "tzpid": "ID9569",
  "title": "Clarifying Note on the Einstein–Rosen Topology Term: R^μν T_μν",
  "uuid": "aa71e21a-46bb-526a-a090-88ef98c99878",
  "PiID": "2578690507643",
  "RTEID": "RTE:P37158.5521:T4.6772",
  "TZPi": "0",
  "PiPE_position": "9576",
  "poloidal_theta_rad": "37158.5521",
  "toroidal_phi_rad": "4.6772",
  "loc_class": "",
  "arxiv_class": "",
  "creator": "Daniel Alexander Trawin",
  "creator_orcid": "https://orcid.org/0009-0001-4630-3715",
  "embedded_at_utc": "2026-06-10T00:42:04+00:00"
}
