{
  "tzpid": "ID8527",
  "title": "GRAVITATIONAL WAVE CARRIER VELOCITY Canonical Statutory Formula: v_GW",
  "uuid": "160cf90f-b3be-516e-a98e-dad0f3a9276b",
  "PiID": "9944697486762",
  "RTEID": "RTE:P33112.2347:T4.2933",
  "TZPi": "7",
  "PiPE_position": "8534",
  "poloidal_theta_rad": "33112.2347",
  "toroidal_phi_rad": "4.2933",
  "loc_class": "",
  "arxiv_class": "",
  "creator": "Daniel Alexander Trawin",
  "creator_orcid": "https://orcid.org/0009-0001-4630-3715",
  "embedded_at_utc": "2026-06-10T00:42:02+00:00"
}
