{
  "tzpid": "ID8187",
  "title": "Observer A: Rotating-Frame Eulerian Observer \\(n^\\mu\\): Beginaligned E^(n) &",
  "uuid": "db5f6a7c-fcee-5d34-aaae-63983e117ed0",
  "PiID": "9393610310291",
  "RTEID": "RTE:P31791.9391:T2.1179",
  "TZPi": "0",
  "PiPE_position": "8194",
  "poloidal_theta_rad": "31791.9391",
  "toroidal_phi_rad": "2.1179",
  "loc_class": "",
  "arxiv_class": "",
  "creator": "Daniel Alexander Trawin",
  "creator_orcid": "https://orcid.org/0009-0001-4630-3715",
  "embedded_at_utc": "2026-06-10T00:42:01+00:00"
}
