{
  "tzpid": "ID7612",
  "title": "Concrete Next Steps I Can Do for You Right Now: m_0,p_0,λ_0",
  "uuid": "45079386-9c16-57ad-a016-34fefd278258",
  "PiID": "0723623464684",
  "RTEID": "RTE:P29559.0865:T4.7220",
  "TZPi": "3",
  "PiPE_position": "7619",
  "poloidal_theta_rad": "29559.0865",
  "toroidal_phi_rad": "4.7220",
  "loc_class": "",
  "arxiv_class": "",
  "creator": "Daniel Alexander Trawin",
  "creator_orcid": "https://orcid.org/0009-0001-4630-3715",
  "embedded_at_utc": "2026-06-10T00:42:00+00:00"
}
