{
  "tzpid": "ID8370",
  "title": "Practical Cautions & Sonic Suggestions: 32/27",
  "uuid": "f260e40d-41d0-58c5-ab9b-e9d477e252f9",
  "PiID": "5471918550464",
  "RTEID": "RTE:P32502.5688:T3.2888",
  "TZPi": "8",
  "PiPE_position": "8377",
  "poloidal_theta_rad": "32502.5688",
  "toroidal_phi_rad": "3.2888",
  "loc_class": "",
  "arxiv_class": "",
  "creator": "Daniel Alexander Trawin",
  "creator_orcid": "https://orcid.org/0009-0001-4630-3715",
  "embedded_at_utc": "2026-06-10T00:42:01+00:00"
}
