{
  "tzpid": "ID0754",
  "title": "THE Update Operator Refresh RATE (hatGamma\\_up)",
  "uuid": "43d801d6-a0be-5ab1-bfc2-d72f4fd5e49e",
  "PiID": "0721134999999",
  "RTEID": "RTE:P2893.0004:T4.7668",
  "TZPi": "4",
  "PiPE_position": "761",
  "poloidal_theta_rad": "2893.0004",
  "toroidal_phi_rad": "4.7668",
  "loc_class": "",
  "arxiv_class": "",
  "creator": "Daniel Alexander Trawin",
  "creator_orcid": "https://orcid.org/0009-0001-4630-3715",
  "embedded_at_utc": "2026-06-10T00:41:42+00:00"
}
