{
  "tzpid": "ID6683",
  "title": "Bessel + Aperture → Spectral Cutoff, Link to Spherical Harmonics",
  "uuid": "2048cc3c-5eff-57b1-9e33-3645320ed4fb",
  "PiID": "5300545058068",
  "RTEID": "RTE:P25951.5731:T5.0611",
  "TZPi": "5",
  "PiPE_position": "6690",
  "poloidal_theta_rad": "25951.5731",
  "toroidal_phi_rad": "5.0611",
  "loc_class": "",
  "arxiv_class": "",
  "creator": "Daniel Alexander Trawin",
  "creator_orcid": "https://orcid.org/0009-0001-4630-3715",
  "embedded_at_utc": "2026-06-10T00:41:57+00:00"
}
