{
  "tzpid": "ID3515",
  "title": "Time-Dependent Radial Relaxation Profile",
  "uuid": "966790a1-ab9d-5546-ae21-1b055d17c33c",
  "PiID": "1639831501970",
  "RTEID": "RTE:P13649.5256:T3.6407",
  "TZPi": "1",
  "PiPE_position": "3522",
  "poloidal_theta_rad": "13649.5256",
  "toroidal_phi_rad": "3.6407",
  "loc_class": "QC - Physics",
  "arxiv_class": "physics.gen-ph",
  "creator": "Daniel Alexander Trawin",
  "creator_orcid": "https://orcid.org/0009-0001-4630-3715",
  "embedded_at_utc": "2026-06-10T00:41:49+00:00"
}
