{
  "tzpid": "ID6043",
  "title": "→ Capacitance Relation",
  "uuid": "06df8446-68a0-5900-be00-15639b7c1b61",
  "PiID": "6455377991403",
  "RTEID": "RTE:P23466.3110:T0.9662",
  "TZPi": "7",
  "PiPE_position": "6050",
  "poloidal_theta_rad": "23466.3110",
  "toroidal_phi_rad": "0.9662",
  "loc_class": "QA - Mathematics: geometry and topology",
  "arxiv_class": "math.DG",
  "creator": "Daniel Alexander Trawin",
  "creator_orcid": "https://orcid.org/0009-0001-4630-3715",
  "embedded_at_utc": "2026-06-10T00:41:56+00:00"
}
