{
  "tzpid": "ID2293",
  "title": "Geometric Enforcement and the Trawin Zero Poin",
  "uuid": "2db6a4f1-9dcf-5403-afe4-5022cd75f31b",
  "PiID": "5124388439045",
  "RTEID": "RTE:P8904.2282:T2.1051",
  "TZPi": "8",
  "PiPE_position": "2300",
  "poloidal_theta_rad": "8904.2282",
  "toroidal_phi_rad": "2.1051",
  "loc_class": "",
  "arxiv_class": "",
  "creator": "Daniel Alexander Trawin",
  "creator_orcid": "https://orcid.org/0009-0001-4630-3715",
  "embedded_at_utc": "2026-06-10T00:41:46+00:00"
}
