{
  "schema": {
    "name": "TZPID ID system sidecar",
    "version": "0.1.0",
    "generated_at_utc": "2026-06-11T06:24:38Z",
    "basis": "TZPID_ID_SYSTEM.csv"
  },
  "identity": {
    "tzpid": "ID10939",
    "title": "Phone2 Category Type Theory Depth I + 0",
    "uuid": "e39383cc-1568-5532-be06-e2bc52ae8646"
  },
  "trawin_geometry": {
    "RTEID": "RTE:P42478.5663:T0.8766",
    "poloidal_theta_rad": "42478.5663",
    "toroidal_phi_rad": "0.8766",
    "rteid_source": "computed"
  },
  "pi_identity": {
    "PiID": "9034711972996",
    "TZPi": "1",
    "PiPE_position": "10946"
  },
  "tzpid_provenance": {
    "project": "TZPID Proof Pipeline",
    "creator": "Daniel Alexander Trawin",
    "creator_orcid": "0009-0001-4630-3715",
    "creator_orcid_url": "https://orcid.org/0009-0001-4630-3715",
    "generator": "mint_phone2_batch1.py",
    "generated_at_utc": "2026-06-11T06:24:38Z"
  }
}