{
  "tzpid": "ID4952",
  "title": "Number Density",
  "uuid": "63514975-ff53-5235-a999-c380b95c4007",
  "PiID": "0541934144737",
  "RTEID": "RTE:P19229.7157:T0.2687",
  "TZPi": "4",
  "PiPE_position": "4959",
  "poloidal_theta_rad": "19229.7157",
  "toroidal_phi_rad": "0.2687",
  "loc_class": "QA - Mathematics: geometry and topology",
  "arxiv_class": "math.DG",
  "creator": "Daniel Alexander Trawin",
  "creator_orcid": "https://orcid.org/0009-0001-4630-3715",
  "embedded_at_utc": "2026-06-10T00:41:53+00:00"
}
