{
  "tzpid": "ID9812",
  "title": "Embedding in the Trawin Hamiltonian: bmθ^(k)",
  "uuid": "a65416d5-448d-5d1f-8c8c-19d3938d4c3e",
  "PiID": "2358502007245",
  "RTEID": "RTE:P38102.1750:T6.2320",
  "TZPi": "2",
  "PiPE_position": "9819",
  "poloidal_theta_rad": "38102.1750",
  "toroidal_phi_rad": "6.2320",
  "loc_class": "",
  "arxiv_class": "",
  "creator": "Daniel Alexander Trawin",
  "creator_orcid": "https://orcid.org/0009-0001-4630-3715",
  "embedded_at_utc": "2026-06-10T00:42:05+00:00"
}
