{
  "tzpid": "ID3996",
  "title": "Delta Expectation Value",
  "uuid": "9f3c3f18-a5d1-5802-8005-7df4aa39aa6f",
  "PiID": "0396665573092",
  "RTEID": "RTE:P15517.3554:T0.4351",
  "TZPi": "5",
  "PiPE_position": "4003",
  "poloidal_theta_rad": "15517.3554",
  "toroidal_phi_rad": "0.4351",
  "loc_class": "QC - Physics",
  "arxiv_class": "physics.gen-ph",
  "creator": "Daniel Alexander Trawin",
  "creator_orcid": "https://orcid.org/0009-0001-4630-3715",
  "embedded_at_utc": "2026-06-10T00:41:50+00:00"
}
