{
  "tzpid": "ID5987",
  "title": "Angular Velocity Relation",
  "uuid": "a0aefdec-d686-5057-93bc-799e4ba4913f",
  "PiID": "5845068772460",
  "RTEID": "RTE:P23248.8506:T0.6078",
  "TZPi": "8",
  "PiPE_position": "5994",
  "poloidal_theta_rad": "23248.8506",
  "toroidal_phi_rad": "0.6078",
  "loc_class": "QC - Physics",
  "arxiv_class": "physics.gen-ph",
  "creator": "Daniel Alexander Trawin",
  "creator_orcid": "https://orcid.org/0009-0001-4630-3715",
  "embedded_at_utc": "2026-06-10T00:41:56+00:00"
}
