{
  "tzpid": "ID5326",
  "title": "Always Needsbuildoutputscache Staging Has Files Relation",
  "uuid": "c7916a0a-a29a-5ea0-a642-42fc3d153a56",
  "PiID": "0386387734317",
  "RTEID": "RTE:P20682.0408:T2.6617",
  "TZPi": "7",
  "PiPE_position": "5333",
  "poloidal_theta_rad": "20682.0408",
  "toroidal_phi_rad": "2.6617",
  "loc_class": "QC - Physics",
  "arxiv_class": "physics.gen-ph",
  "creator": "Daniel Alexander Trawin",
  "creator_orcid": "https://orcid.org/0009-0001-4630-3715",
  "embedded_at_utc": "2026-06-10T00:41:54+00:00"
}
