{
  "tzpid": "ID3532",
  "title": "Quantum Quantum State Functional",
  "uuid": "b952589b-662c-5e49-8001-68864c2145fa",
  "PiID": "5116851714376",
  "RTEID": "RTE:P13715.5404:T3.7494",
  "TZPi": "1",
  "PiPE_position": "3539",
  "poloidal_theta_rad": "13715.5404",
  "toroidal_phi_rad": "3.7494",
  "loc_class": "QC - Physics: quantum theory",
  "arxiv_class": "quant-ph",
  "creator": "Daniel Alexander Trawin",
  "creator_orcid": "https://orcid.org/0009-0001-4630-3715",
  "embedded_at_utc": "2026-06-10T00:41:49+00:00"
}
