{
  "schema": {
    "name": "TZPID ID system sidecar",
    "version": "0.1.0",
    "generated_at_utc": "2026-06-11T06:24:39Z",
    "basis": "TZPID_ID_SYSTEM.csv"
  },
  "identity": {
    "tzpid": "ID11020",
    "title": "Phone2 Category Type Theory Fairness WF Vars Next",
    "uuid": "d187139f-76b5-5d12-9f24-52cf6c633278"
  },
  "trawin_geometry": {
    "RTEID": "RTE:P42793.1073:T1.3948",
    "poloidal_theta_rad": "42793.1073",
    "toroidal_phi_rad": "1.3948",
    "rteid_source": "computed"
  },
  "pi_identity": {
    "PiID": "6427287573946",
    "TZPi": "7",
    "PiPE_position": "11027"
  },
  "tzpid_provenance": {
    "project": "TZPID Proof Pipeline",
    "creator": "Daniel Alexander Trawin",
    "creator_orcid": "0009-0001-4630-3715",
    "creator_orcid_url": "https://orcid.org/0009-0001-4630-3715",
    "generator": "mint_phone2_batch1.py",
    "generated_at_utc": "2026-06-11T06:24:39Z"
  }
}