{
  "schema": {
    "name": "TZPID source truth prototype",
    "version": "0.2.1",
    "generated_at": "2026-06-17T04:22:25+00:00",
    "source": "paper_xvii_wa_derivation_intake",
    "non_destructive": true
  },
  "identity": {
    "tzpid": "ID11694",
    "uuid": "70e75189-66da-51df-b79c-9531297322fe",
    "registry_id": "registry_id_11694",
    "piid": "PiID-11694-paper-xvii-wa-derivation",
    "canonical_title": "Paper XVII Naive Nested Vacuum Branch",
    "source_files": {
      "paper_xvii": "D:\\TZPIDProof\\peer_review\\TZPID_Papers_XI_XIX\\Paper_XVII_wa_Derivation.tex",
      "source_truth": "D:\\TZPIDProof\\tzp_id\\ID11694\\ID11694.source_truth.json"
    }
  },
  "creator": {
    "name": "Daniel Alexander Trawin",
    "orcid": "https://orcid.org/0009-0001-4630-3715"
  },
  "classification": {
    "category": "paper-xvii-wa-derivation",
    "discipline": "cosmology; dark energy; formal verification",
    "loc_class": "QB - Astronomy",
    "arxiv_class": "astro-ph.CO; gr-qc"
  },
  "theory": {
    "canonical_statement": "A naive nested-vacuum branch scales as inverse fourth power of the scale factor.",
    "technical_interpretation": "Paper XVII w(a) derivation carrier: A naive nested-vacuum branch scales as inverse fourth power of the scale factor.",
    "source_lineage": "Extracted from Paper XVII w(a) Derivation."
  },
  "canonical_equation": {
    "latex_blocks": [
      "\\rho_X(a)\\propto a^{-4}"
    ],
    "source_section_latex": "\\rho_X(a)\\propto a^{-4}"
  },
  "proof_lane": {
    "isabelle_kind": "Scaling_Law",
    "obligation_role": "Branch_Test",
    "required_checks": [
      "source_traceability",
      "hol_carrier_typing",
      "dark_energy_sign_check"
    ],
    "wolfram_status": "semantic_carrier_registered;paper_xvii_wa_derivation_intake",
    "isabelle_sid": "11694",
    "isabelle_theory": "TZPID_PaperXVII_wa_Derivation.thy"
  },
  "wolfram_status": "semantic_carrier_registered;paper_xvii_wa_derivation_intake",
  "metadata": {
    "creator": "Daniel Alexander Trawin",
    "orcid": "https://orcid.org/0009-0001-4630-3715",
    "generated_at": "2026-06-17T04:22:25+00:00",
    "wolfram_status": "semantic_carrier_registered;paper_xvii_wa_derivation_intake"
  }
}