{
  "schema": {
    "name": "TZPID ID system sidecar",
    "version": "0.1.0",
    "generated_at_utc": "2026-06-11T06:24:39Z",
    "basis": "TZPID_ID_SYSTEM.csv"
  },
  "identity": {
    "tzpid": "ID11035",
    "title": "Phone2 Category Type Theory GPU Cat Category",
    "uuid": "220f0d66-c54a-5f6f-bb64-00e2b31b0147"
  },
  "trawin_geometry": {
    "RTEID": "RTE:P42851.3556:T1.4908",
    "poloidal_theta_rad": "42851.3556",
    "toroidal_phi_rad": "1.4908",
    "rteid_source": "computed"
  },
  "pi_identity": {
    "PiID": "4272534366941",
    "TZPi": "4",
    "PiPE_position": "11042"
  },
  "tzpid_provenance": {
    "project": "TZPID Proof Pipeline",
    "creator": "Daniel Alexander Trawin",
    "creator_orcid": "0009-0001-4630-3715",
    "creator_orcid_url": "https://orcid.org/0009-0001-4630-3715",
    "generator": "mint_phone2_batch1.py",
    "generated_at_utc": "2026-06-11T06:24:39Z"
  }
}