{
  "tzpid": "ID7424",
  "title": "Key Numeric Results (Final Order Parameter R After 50 Years): k_0: k_0=0.001",
  "uuid": "9d02b752-771f-5b73-b0f8-e26e160110fd",
  "PiID": "7815478181152",
  "RTEID": "RTE:P28829.0407:T3.5191",
  "TZPi": "8",
  "PiPE_position": "7431",
  "poloidal_theta_rad": "28829.0407",
  "toroidal_phi_rad": "3.5191",
  "loc_class": "",
  "arxiv_class": "",
  "creator": "Daniel Alexander Trawin",
  "creator_orcid": "https://orcid.org/0009-0001-4630-3715",
  "embedded_at_utc": "2026-06-10T00:41:59+00:00"
}
