{
  "tzpid": "ID7093",
  "title": "Worked Numeric Examples You Can Plug into an Experiment: 1.64×10^-24",
  "uuid": "b5ca2e77-959d-5991-836b-fe48604dda3a",
  "PiID": "6883834363465",
  "RTEID": "RTE:P27543.6942:T1.4012",
  "TZPi": "4",
  "PiPE_position": "7100",
  "poloidal_theta_rad": "27543.6942",
  "toroidal_phi_rad": "1.4012",
  "loc_class": "",
  "arxiv_class": "",
  "creator": "Daniel Alexander Trawin",
  "creator_orcid": "https://orcid.org/0009-0001-4630-3715",
  "embedded_at_utc": "2026-06-10T00:41:58+00:00"
}
