{
  "tzpid": "ID4458",
  "title": "Curvature Relation",
  "uuid": "049ed674-776b-5cd7-b716-50b7b3923b28",
  "PiID": "0304639947132",
  "RTEID": "RTE:P17311.4040:T3.3911",
  "TZPi": "9",
  "PiPE_position": "4465",
  "poloidal_theta_rad": "17311.4040",
  "toroidal_phi_rad": "3.3911",
  "loc_class": "QC - Physics: relativity and gravitation",
  "arxiv_class": "gr-qc",
  "creator": "Daniel Alexander Trawin",
  "creator_orcid": "https://orcid.org/0009-0001-4630-3715",
  "embedded_at_utc": "2026-06-10T00:41:52+00:00"
}
