{
  "tzpid": "ID6726",
  "title": "Practical Measurement Algorithm You Can Run on Any Image (No EXIF Needed): θ_1",
  "uuid": "45fda8b5-5863-597e-9f88-d29b068b1573",
  "PiID": "4903982059551",
  "RTEID": "RTE:P26118.5517:T5.3362",
  "TZPi": "2",
  "PiPE_position": "6733",
  "poloidal_theta_rad": "26118.5517",
  "toroidal_phi_rad": "5.3362",
  "loc_class": "",
  "arxiv_class": "",
  "creator": "Daniel Alexander Trawin",
  "creator_orcid": "https://orcid.org/0009-0001-4630-3715",
  "embedded_at_utc": "2026-06-10T00:41:58+00:00"
}
