{
  "tzpid": "ID4541",
  "title": "Coupled Quantum Hamiltonian Laplacian Operator",
  "uuid": "23bcf9e7-2a8b-5890-886b-3cc876698557",
  "PiID": "8708085990480",
  "RTEID": "RTE:P17633.7115:T3.9222",
  "TZPi": "5",
  "PiPE_position": "4548",
  "poloidal_theta_rad": "17633.7115",
  "toroidal_phi_rad": "3.9222",
  "loc_class": "QA - Mathematics: geometry and topology",
  "arxiv_class": "math.DG",
  "creator": "Daniel Alexander Trawin",
  "creator_orcid": "https://orcid.org/0009-0001-4630-3715",
  "embedded_at_utc": "2026-06-10T00:41:52+00:00"
}
