{
  "tzpid": "ID8346",
  "title": "How \\(r\\) Can Act as a Bridge / Flip / Twist for DAANS: φ Mapsto φ+π",
  "uuid": "5d5e2f8b-5a00-50ac-b13a-0c068b1e867a",
  "PiID": "7034436619910",
  "RTEID": "RTE:P32409.3715:T3.1352",
  "TZPi": "6",
  "PiPE_position": "8353",
  "poloidal_theta_rad": "32409.3715",
  "toroidal_phi_rad": "3.1352",
  "loc_class": "",
  "arxiv_class": "",
  "creator": "Daniel Alexander Trawin",
  "creator_orcid": "https://orcid.org/0009-0001-4630-3715",
  "embedded_at_utc": "2026-06-10T00:42:01+00:00"
}
