{
  "tzpid": "ID4359",
  "title": "Relation: a_0∼1.2×10^-10,m/s^2",
  "uuid": "96969df2-dee2-5aa5-98bc-0b07c637c22c",
  "PiID": "7615814002501",
  "RTEID": "RTE:P16926.9650:T2.7577",
  "TZPi": "4",
  "PiPE_position": "4366",
  "poloidal_theta_rad": "16926.9650",
  "toroidal_phi_rad": "2.7577",
  "loc_class": "QA - Mathematics: geometry and topology",
  "arxiv_class": "math.DG",
  "creator": "Daniel Alexander Trawin",
  "creator_orcid": "https://orcid.org/0009-0001-4630-3715",
  "embedded_at_utc": "2026-06-10T00:41:51+00:00"
}
