{
  "tzpid": "ID2655",
  "title": "Incorporating New Information into Knowledgebase",
  "uuid": "68c5050b-34ad-5913-b902-66fdd11ba981",
  "PiID": "8048575640142",
  "RTEID": "RTE:P10309.9546:T4.4213",
  "TZPi": "5",
  "PiPE_position": "2662",
  "poloidal_theta_rad": "10309.9546",
  "toroidal_phi_rad": "4.4213",
  "loc_class": "",
  "arxiv_class": "",
  "creator": "Daniel Alexander Trawin",
  "creator_orcid": "https://orcid.org/0009-0001-4630-3715",
  "embedded_at_utc": "2026-06-10T00:41:47+00:00"
}
