{
  "tzpid": "ID9372",
  "title": "Relation: Textbackslash textT4textbackslash,∫ 0ˆωtextbackslash textcutη(ω)textbackslas",
  "uuid": "3d55ec90-cb28-51b5-b8cd-49e917f04f03",
  "PiID": "8783076670944",
  "RTEID": "RTE:P36393.5573:T3.4167",
  "TZPi": "6",
  "PiPE_position": "9379",
  "poloidal_theta_rad": "36393.5573",
  "toroidal_phi_rad": "3.4167",
  "loc_class": "",
  "arxiv_class": "",
  "creator": "Daniel Alexander Trawin",
  "creator_orcid": "https://orcid.org/0009-0001-4630-3715",
  "embedded_at_utc": "2026-06-10T00:42:04+00:00"
}
