[
	{
		"id":"ID0006",
		"block_index":1,
		"status":"pass",
		"wolfram_input":"uT==ContourIntegralGamma*Sqrt[Abs[g]]*dell",
		"paper_keys":[
			"paper07",
			"paper10"
		],
		"source_method":"InputForm"
	},
	{
		"id":"ID0006",
		"block_index":2,
		"status":"pass",
		"wolfram_input":"WindP[Gamma]==1",
		"paper_keys":[
			"paper07",
			"paper10"
		],
		"source_method":"InputForm"
	},
	{
		"id":"ID0006",
		"block_index":3,
		"status":"pass",
		"wolfram_input":"uTNorm==NormalizeTRAWINTuple[ContourIntegralGammaSqrt[Abs[g]]*dell,WindP[Gamma]==1,SimilarTo[Gamma,Lambda]]",
		"paper_keys":[
			"paper07",
			"paper10"
		],
		"source_method":"InputForm"
	},
	{
		"id":"ID0007",
		"block_index":1,
		"status":"pass",
		"wolfram_input":"alphaT==((dt')\/(dt))",
		"paper_keys":[
			"paper10"
		],
		"source_method":"InputForm"
	},
	{
		"id":"ID0007",
		"block_index":2,
		"status":"pass",
		"wolfram_input":"alphaT^(TZP)==LimitGammap[(dt')\/(dt)]",
		"paper_keys":[
			"paper10"
		],
		"source_method":"InputForm"
	},
	{
		"id":"ID0007",
		"block_index":3,
		"status":"pass",
		"wolfram_input":"alphaTNorm==NormalizeTRAWIN[((dt')\/(dt)),LimitGammap[(dt')\/(dt)],uT]",
		"paper_keys":[
			"paper10"
		],
		"source_method":"InputForm"
	},
	{
		"id":"ID0012",
		"block_index":1,
		"status":"pass",
		"wolfram_input":"C[phi1,phi2]==(Tuple[Abs[Inner[phi1,phi2]]]\/(phi1*phi2))",
		"paper_keys":[
			"paper10"
		],
		"source_method":"InputForm"
	},
	{
		"id":"ID0012",
		"block_index":2,
		"status":"pass",
		"wolfram_input":"phi==Sqrt[Inner[phi,phi]]",
		"paper_keys":[
			"paper10"
		],
		"source_method":"InputForm"
	},
	{
		"id":"ID0012",
		"block_index":3,
		"status":"pass",
		"wolfram_input":"Inner[phi1,phi2]",
		"paper_keys":[
			"paper10"
		],
		"source_method":"InputForm"
	},
	{
		"id":"ID0024",
		"block_index":1,
		"status":"pass",
		"wolfram_input":"rhoVac^(T)==((1)\/(uT^(4)))*Integral0^(omegaCut)eta[omega]*hbaromega*domega",
		"paper_keys":[
			"paper06",
			"paper07"
		],
		"source_method":"InputForm"
	},
	{
		"id":"ID0024",
		"block_index":2,
		"status":"pass",
		"wolfram_input":"omegaCut==omegaCut[SHD]",
		"paper_keys":[
			"paper06",
			"paper07"
		],
		"source_method":"InputForm"
	},
	{
		"id":"ID0024",
		"block_index":3,
		"status":"pass",
		"wolfram_input":"eta[omega]",
		"paper_keys":[
			"paper06",
			"paper07"
		],
		"source_method":"InputForm"
	},
	{
		"id":"ID0024",
		"block_index":4,
		"status":"pass",
		"wolfram_input":"Integral0^(omegaCut)eta[omega]*hbaromega*domega",
		"paper_keys":[
			"paper06",
			"paper07"
		],
		"source_method":"InputForm"
	},
	{
		"id":"ID0037",
		"block_index":1,
		"status":"pass",
		"wolfram_input":"L==IntegralV[r*J]*d^(3)x",
		"paper_keys":[
			"paper02",
			"paper04"
		],
		"source_method":"InputForm"
	},
	{
		"id":"ID0037",
		"block_index":2,
		"status":"pass",
		"wolfram_input":"((dL)\/(dt))==IntegralV[J*B]*d^(3)x",
		"paper_keys":[
			"paper02",
			"paper04"
		],
		"source_method":"InputForm"
	},
	{
		"id":"ID0037",
		"block_index":3,
		"status":"pass",
		"wolfram_input":"L*rightarrowPair[J,B]",
		"paper_keys":[
			"paper02",
			"paper04"
		],
		"source_method":"InputForm"
	},
	{
		"id":"ID0038",
		"block_index":1,
		"status":"pass",
		"wolfram_input":"Lambda==((B^(2))\/(rho*mu*Omega^(2)))",
		"paper_keys":[
			"paper02",
			"paper04"
		],
		"source_method":"InputForm"
	},
	{
		"id":"ID0038",
		"block_index":2,
		"status":"pass",
		"wolfram_input":"Lambda==1",
		"paper_keys":[
			"paper02",
			"paper04"
		],
		"source_method":"InputForm"
	},
	{
		"id":"ID0038",
		"block_index":3,
		"status":"pass",
		"wolfram_input":"Lambda->1",
		"paper_keys":[
			"paper02",
			"paper04"
		],
		"source_method":"InputForm"
	},
	{
		"id":"ID0039",
		"block_index":1,
		"status":"pass",
		"wolfram_input":"((B^(2))\/(2*mu))==((1)\/(2))rho[Omega*r]^(2)",
		"paper_keys":[
			"paper02",
			"paper04"
		],
		"source_method":"InputForm"
	},
	{
		"id":"ID0039",
		"block_index":2,
		"status":"pass",
		"wolfram_input":"EMag==ERot",
		"paper_keys":[
			"paper02",
			"paper04"
		],
		"source_method":"InputForm"
	},
	{
		"id":"ID0039",
		"block_index":3,
		"status":"pass",
		"wolfram_input":"((B^(2))\/(2*mu))",
		"paper_keys":[
			"paper02",
			"paper04"
		],
		"source_method":"InputForm"
	},
	{
		"id":"ID0039",
		"block_index":4,
		"status":"pass",
		"wolfram_input":"((1)\/(2))rho[Omega*r]^(2)",
		"paper_keys":[
			"paper02",
			"paper04"
		],
		"source_method":"InputForm"
	},
	{
		"id":"ID0040",
		"block_index":1,
		"status":"pass",
		"wolfram_input":"Lambda==((B^(2))\/(rho*mu*Omega^(2)))",
		"paper_keys":[
			"paper04",
			"paper10"
		],
		"source_method":"InputForm"
	},
	{
		"id":"ID0040",
		"block_index":2,
		"status":"pass",
		"wolfram_input":"LambdaCrit==1",
		"paper_keys":[
			"paper04",
			"paper10"
		],
		"source_method":"InputForm"
	},
	{
		"id":"ID0040",
		"block_index":3,
		"status":"pass",
		"wolfram_input":"Abs[Lambda-1]<=epsilonSys",
		"paper_keys":[
			"paper04",
			"paper10"
		],
		"source_method":"InputForm"
	},
	{
		"id":"ID0044",
		"block_index":1,
		"status":"pass",
		"wolfram_input":"mu==k*MR^(2)Omega",
		"paper_keys":[
			"paper02",
			"paper04"
		],
		"source_method":"InputForm"
	},
	{
		"id":"ID0044",
		"block_index":2,
		"status":"pass",
		"wolfram_input":"k==const",
		"paper_keys":[
			"paper02",
			"paper04"
		],
		"source_method":"InputForm"
	},
	{
		"id":"ID0044",
		"block_index":3,
		"status":"pass",
		"wolfram_input":"M*R^(2)Omega",
		"paper_keys":[
			"paper02",
			"paper04"
		],
		"source_method":"InputForm"
	},
	{
		"id":"ID0044",
		"block_index":4,
		"status":"pass",
		"wolfram_input":"k==((mu)\/(M*R^(2)Omega))",
		"paper_keys":[
			"paper02",
			"paper04"
		],
		"source_method":"InputForm"
	},
	{
		"id":"ID0045",
		"block_index":1,
		"status":"pass",
		"wolfram_input":"gMu==((mu)\/(M*R^(2)Omega))",
		"paper_keys":[
			"paper04"
		],
		"source_method":"InputForm"
	},
	{
		"id":"ID0045",
		"block_index":2,
		"status":"pass",
		"wolfram_input":"gMu==O[1]",
		"paper_keys":[
			"paper04"
		],
		"source_method":"InputForm"
	},
	{
		"id":"ID0045",
		"block_index":3,
		"status":"pass",
		"wolfram_input":"mu",
		"paper_keys":[
			"paper04"
		],
		"source_method":"InputForm"
	},
	{
		"id":"ID0045",
		"block_index":4,
		"status":"pass",
		"wolfram_input":"M*R^(2)Omega",
		"paper_keys":[
			"paper04"
		],
		"source_method":"InputForm"
	},
	{
		"id":"ID0045",
		"block_index":5,
		"status":"pass",
		"wolfram_input":"gMu==((mu)\/(M*R^(2)Omega))==O[1]",
		"paper_keys":[
			"paper04"
		],
		"source_method":"InputForm"
	},
	{
		"id":"ID0068",
		"block_index":1,
		"status":"pass",
		"wolfram_input":"gammaB==iContourIntegralGammaInner[psi,GradLambdapsi]*dlambda",
		"paper_keys":[
			"paper03"
		],
		"source_method":"InputForm"
	},
	{
		"id":"ID0068",
		"block_index":2,
		"status":"pass",
		"wolfram_input":"gammaTot==gammaDyn+gammaB+gammaL",
		"paper_keys":[
			"paper03"
		],
		"source_method":"InputForm"
	},
	{
		"id":"ID0068",
		"block_index":3,
		"status":"pass",
		"wolfram_input":"Gamma",
		"paper_keys":[
			"paper03"
		],
		"source_method":"InputForm"
	},
	{
		"id":"ID0078",
		"block_index":1,
		"status":"pass",
		"wolfram_input":"SimilarTo[Inner[O[x]O[0]],Abs[x]^(-2+eta)]",
		"paper_keys":[
			"paper01"
		],
		"source_method":"InputForm"
	},
	{
		"id":"ID0078",
		"block_index":2,
		"status":"pass",
		"wolfram_input":"eta==eta[dEff,TZP]",
		"paper_keys":[
			"paper01"
		],
		"source_method":"InputForm"
	},
	{
		"id":"ID0078",
		"block_index":3,
		"status":"pass",
		"wolfram_input":"O[x]",
		"paper_keys":[
			"paper01"
		],
		"source_method":"InputForm"
	},
	{
		"id":"ID0085",
		"block_index":1,
		"status":"pass",
		"wolfram_input":"tauEm==Integral*r*(J*B+rhoEE)*dV",
		"paper_keys":[
			"paper04"
		],
		"source_method":"InputForm"
	},
	{
		"id":"ID0085",
		"block_index":2,
		"status":"pass",
		"wolfram_input":"((dL)\/(dt))==tauEm",
		"paper_keys":[
			"paper04"
		],
		"source_method":"InputForm"
	},
	{
		"id":"ID0085",
		"block_index":3,
		"status":"pass",
		"wolfram_input":"J*B+rhoEE",
		"paper_keys":[
			"paper04"
		],
		"source_method":"InputForm"
	},
	{
		"id":"ID0087",
		"block_index":1,
		"status":"pass",
		"wolfram_input":"dot[omega](t)==((tauEm[t])\/(IT))",
		"paper_keys":[
			"paper02",
			"paper04"
		],
		"source_method":"InputForm"
	},
	{
		"id":"ID0087",
		"block_index":2,
		"status":"pass",
		"wolfram_input":"omega[t]==omega[0]+((1)\/(IT))Integral0^(t)tauEm[t']*dt'",
		"paper_keys":[
			"paper02",
			"paper04"
		],
		"source_method":"InputForm"
	},
	{
		"id":"ID0087",
		"block_index":3,
		"status":"pass",
		"wolfram_input":"tauEm[t]",
		"paper_keys":[
			"paper02",
			"paper04"
		],
		"source_method":"InputForm"
	},
	{
		"id":"ID0089",
		"block_index":1,
		"status":"pass",
		"wolfram_input":"F[mathbfLabGyro] -> mathbfAstroRot",
		"paper_keys":[
			"paper02",
			"paper04"
		],
		"source_method":"InputForm"
	},
	{
		"id":"ID0089",
		"block_index":2,
		"status":"pass",
		"wolfram_input":"F[gcirc*f]==F[g]circ*F[f]&&eta:F->G",
		"paper_keys":[
			"paper02",
			"paper04"
		],
		"source_method":"InputForm"
	},
	{
		"id":"ID0089",
		"block_index":3,
		"status":"pass",
		"wolfram_input":"F[gcirc*f]==F[g]circ*F[f]",
		"paper_keys":[
			"paper02",
			"paper04"
		],
		"source_method":"InputForm"
	},
	{
		"id":"ID0089",
		"block_index":4,
		"status":"pass",
		"wolfram_input":"eta:F->G",
		"paper_keys":[
			"paper02",
			"paper04"
		],
		"source_method":"InputForm"
	},
	{
		"id":"ID0090",
		"block_index":1,
		"status":"pass",
		"wolfram_input":"PiK^(lab)==PiK^(astro)",
		"paper_keys":[
			"paper02",
			"paper04"
		],
		"source_method":"InputForm"
	},
	{
		"id":"ID0090",
		"block_index":2,
		"status":"pass",
		"wolfram_input":"Fscale[Slab] -> Sastro",
		"paper_keys":[
			"paper02",
			"paper04"
		],
		"source_method":"InputForm"
	},
	{
		"id":"ID0090",
		"block_index":3,
		"status":"pass",
		"wolfram_input":"PiK^(lab)",
		"paper_keys":[
			"paper02",
			"paper04"
		],
		"source_method":"InputForm"
	},
	{
		"id":"ID0092",
		"block_index":1,
		"status":"pass",
		"wolfram_input":"G==SO[3]*ltimesPhi*U[1]",
		"paper_keys":[
			"paper04"
		],
		"source_method":"InputForm"
	},
	{
		"id":"ID0092",
		"block_index":2,
		"status":"pass",
		"wolfram_input":"Tuple[R,Exp[I*alpha]]*Tuple[R',Exp[I*beta]]==Tuple[RR',Exp[I*alpha]*phiR[Exp[I*beta]]]",
		"paper_keys":[
			"paper04"
		],
		"source_method":"InputForm"
	},
	{
		"id":"ID0092",
		"block_index":3,
		"status":"pass",
		"wolfram_input":"TZPSequence[SO[3],U[1]]",
		"paper_keys":[
			"paper04"
		],
		"source_method":"InputForm"
	},
	{
		"id":"ID0093",
		"block_index":1,
		"status":"pass",
		"wolfram_input":"phiT^(ast)omega==omega",
		"paper_keys":[
			"paper04"
		],
		"source_method":"InputForm"
	},
	{
		"id":"ID0093",
		"block_index":2,
		"status":"pass",
		"wolfram_input":"LXHomega==0",
		"paper_keys":[
			"paper04"
		],
		"source_method":"InputForm"
	},
	{
		"id":"ID0093",
		"block_index":3,
		"status":"pass",
		"wolfram_input":"XH",
		"paper_keys":[
			"paper04"
		],
		"source_method":"InputForm"
	},
	{
		"id":"ID0099",
		"block_index":1,
		"status":"pass",
		"wolfram_input":"$psiBeat[t]==2*Cos[Pi[f2-f1]t]Sin[Pi[f1+f2]t]$",
		"paper_keys":[
			"paper02"
		],
		"source_method":"InputForm"
	},
	{
		"id":"ID0099",
		"block_index":2,
		"status":"pass",
		"wolfram_input":"TZPSequence[$Delta*f==Abs[f2-f1],bar*f==((f1+f2)\/(2))$]",
		"paper_keys":[
			"paper02"
		],
		"source_method":"InputForm"
	},
	{
		"id":"ID0099",
		"block_index":3,
		"status":"pass",
		"wolfram_input":"$tN==((n)\/(2*Delta*f))(440\/446*Hz:tN==((n)\/(12)))$",
		"paper_keys":[
			"paper02"
		],
		"source_method":"InputForm"
	},
	{
		"id":"ID0105",
		"block_index":1,
		"status":"pass",
		"wolfram_input":"SSync[rho,theta,Phi]==IntegralM[alpha*Abs[Grad*theta]^2+beta*D[rhoVertsigma]+gamma*Abs[PhiBulk-PhiBdy]^2]*dmu",
		"paper_keys":[
			"paper02"
		],
		"source_method":"InputForm"
	},
	{
		"id":"ID0105",
		"block_index":2,
		"status":"pass",
		"wolfram_input":"DiracDelta*SSync==0",
		"paper_keys":[
			"paper02"
		],
		"source_method":"InputForm"
	},
	{
		"id":"ID0105",
		"block_index":3,
		"status":"pass",
		"wolfram_input":"IntegralM*alpha*Abs[Grad*theta]^2*dmu",
		"paper_keys":[
			"paper02"
		],
		"source_method":"InputForm"
	},
	{
		"id":"ID0105",
		"block_index":4,
		"status":"pass",
		"wolfram_input":"IntegralM*beta*D[rhoVertsigma]*dmu",
		"paper_keys":[
			"paper02"
		],
		"source_method":"InputForm"
	},
	{
		"id":"ID0115",
		"block_index":1,
		"status":"pass",
		"wolfram_input":"dot[theta]_i==omegaI+((K)\/(N))SumJ1^(N)AIjSin[thetaJ-thetaI]",
		"paper_keys":[
			"paper01",
			"paper02"
		],
		"source_method":"InputForm"
	},
	{
		"id":"ID0115",
		"block_index":2,
		"status":"pass",
		"wolfram_input":"AIj==((Sqrt[mI*mJ])\/(Abs[aI-aJ]))",
		"paper_keys":[
			"paper01",
			"paper02"
		],
		"source_method":"InputForm"
	},
	{
		"id":"ID0115",
		"block_index":3,
		"status":"pass",
		"wolfram_input":"N==8",
		"paper_keys":[
			"paper01",
			"paper02"
		],
		"source_method":"InputForm"
	},
	{
		"id":"ID0117",
		"block_index":1,
		"status":"pass",
		"wolfram_input":"r*Exp[I*psi]==((1)\/(N))SumJ1^(N)Exp[I*thetaJ]",
		"paper_keys":[
			"paper02"
		],
		"source_method":"InputForm"
	},
	{
		"id":"ID0117",
		"block_index":2,
		"status":"pass",
		"wolfram_input":"r==Abs[((1)\/(N))SumJ1^(N)Exp[I*thetaJ]]",
		"paper_keys":[
			"paper02"
		],
		"source_method":"InputForm"
	},
	{
		"id":"ID0117",
		"block_index":3,
		"status":"pass",
		"wolfram_input":"psi==arg[((1)\/(N))SumJ1^(N)Exp[I*thetaJ]]",
		"paper_keys":[
			"paper02"
		],
		"source_method":"InputForm"
	},
	{
		"id":"ID0120",
		"block_index":1,
		"status":"pass",
		"wolfram_input":"dot[theta]_i==OmegaI+((KS)\/(N))SumJ1^(N)Sin[thetaJ-thetaI]+lambdaISin[phiI-thetaI]",
		"paper_keys":[
			"paper02"
		],
		"source_method":"InputForm"
	},
	{
		"id":"ID0120",
		"block_index":2,
		"status":"pass",
		"wolfram_input":"dot[phi]_i==nuI+((KO)\/(N))SumJ1^(N)Sin[phiJ-phiI]",
		"paper_keys":[
			"paper02"
		],
		"source_method":"InputForm"
	},
	{
		"id":"ID0120",
		"block_index":3,
		"status":"pass",
		"wolfram_input":"XI==Pair[thetaI,phiI]",
		"paper_keys":[
			"paper02"
		],
		"source_method":"InputForm"
	},
	{
		"id":"ID0143",
		"block_index":1,
		"status":"pass",
		"wolfram_input":"((OmegaSpin)\/(OmegaOrb))==((3)\/(2))",
		"paper_keys":[
			"paper01",
			"paper02",
			"paper03",
			"paper04"
		],
		"source_method":"InputForm"
	},
	{
		"id":"ID0143",
		"block_index":2,
		"status":"pass",
		"wolfram_input":"Proportional[tauTidal,-gamma*Sin[2*theta-3*M]]",
		"paper_keys":[
			"paper01",
			"paper02",
			"paper03",
			"paper04"
		],
		"source_method":"InputForm"
	},
	{
		"id":"ID0143",
		"block_index":3,
		"status":"pass",
		"wolfram_input":"dot[theta]==OmegaSpin+tauTidal",
		"paper_keys":[
			"paper01",
			"paper02",
			"paper03",
			"paper04"
		],
		"source_method":"InputForm"
	},
	{
		"id":"ID0144",
		"block_index":1,
		"status":"pass",
		"wolfram_input":"Element[K0,Commutator[KMin,KMax]]",
		"paper_keys":[
			"paper02",
			"paper04"
		],
		"source_method":"InputForm"
	},
	{
		"id":"ID0144",
		"block_index":2,
		"status":"pass",
		"wolfram_input":"r[t;K0]==Abs[((1)\/(N))SumJ1^(N)Exp[I*thetaJ[t;K0]]]",
		"paper_keys":[
			"paper02",
			"paper04"
		],
		"source_method":"InputForm"
	},
	{
		"id":"ID0144",
		"block_index":3,
		"status":"pass",
		"wolfram_input":"OmegaCluster[K0]==(dot[theta]_j:Abs[dot[theta]_j-dot[theta]_k]<epsilon)",
		"paper_keys":[
			"paper02",
			"paper04"
		],
		"source_method":"InputForm"
	},
	{
		"id":"ID0187",
		"block_index":1,
		"status":"pass",
		"wolfram_input":"PVac>PCrit",
		"paper_keys":[
			"paper07",
			"paper08"
		],
		"source_method":"InputForm"
	},
	{
		"id":"ID0187",
		"block_index":2,
		"status":"pass",
		"wolfram_input":"BTZP!=0",
		"paper_keys":[
			"paper07",
			"paper08"
		],
		"source_method":"InputForm"
	},
	{
		"id":"ID0187",
		"block_index":3,
		"status":"pass",
		"wolfram_input":"TZPNormalizeWrap[PVac,PCrit]",
		"paper_keys":[
			"paper07",
			"paper08"
		],
		"source_method":"InputForm"
	},
	{
		"id":"ID0256",
		"block_index":1,
		"status":"pass",
		"wolfram_input":"Element[TZPSequence[fN==n*f1,n],Z0]",
		"paper_keys":[
			"paper01"
		],
		"source_method":"InputForm"
	},
	{
		"id":"ID0256",
		"block_index":2,
		"status":"pass",
		"wolfram_input":"omega^(2)==k^(2)vA^(2)[1+(((omegaGyro)\/(omega)))^(2)]",
		"paper_keys":[
			"paper01"
		],
		"source_method":"InputForm"
	},
	{
		"id":"ID0285",
		"block_index":1,
		"status":"pass",
		"wolfram_input":"MDAANS==Q*C",
		"paper_keys":[
			"paper01"
		],
		"source_method":"InputForm"
	},
	{
		"id":"ID0285",
		"block_index":2,
		"status":"pass",
		"wolfram_input":"Dim[MDAANS]==153600",
		"paper_keys":[
			"paper01"
		],
		"source_method":"InputForm"
	},
	{
		"id":"ID0285",
		"block_index":3,
		"status":"pass",
		"wolfram_input":"ETZP[MDAANS] -> T",
		"paper_keys":[
			"paper01"
		],
		"source_method":"InputForm"
	},
	{
		"id":"ID0285",
		"block_index":4,
		"status":"pass",
		"wolfram_input":"ETZP[MDAANS] -> T",
		"paper_keys":[
			"paper01"
		],
		"source_method":"InputForm"
	},
	{
		"id":"ID0353",
		"block_index":1,
		"status":"pass",
		"wolfram_input":"SimilarTo[P[s],s^(-tau)f[s\/sC]]",
		"paper_keys":[
			"paper01"
		],
		"source_method":"InputForm"
	},
	{
		"id":"ID0353",
		"block_index":2,
		"status":"pass",
		"wolfram_input":"tau==tauAst",
		"paper_keys":[
			"paper01"
		],
		"source_method":"InputForm"
	},
	{
		"id":"ID0353",
		"block_index":3,
		"status":"pass",
		"wolfram_input":"SimilarTo[sC,L^(D)]",
		"paper_keys":[
			"paper01"
		],
		"source_method":"InputForm"
	},
	{
		"id":"ID0388",
		"block_index":1,
		"status":"pass",
		"wolfram_input":"H^2(a)==H0^2[OmegaM*a^(-3)+OmegaR*a^(-4)+OmegaK*a^(-2)+Omega_Lambda]",
		"paper_keys":[
			"paper08"
		],
		"source_method":"InputForm"
	},
	{
		"id":"ID0388",
		"block_index":2,
		"status":"pass",
		"wolfram_input":"DC[z]==cIntegral0^(z)((dz')\/(H[z']))",
		"paper_keys":[
			"paper08"
		],
		"source_method":"InputForm"
	},
	{
		"id":"ID0388",
		"block_index":3,
		"status":"pass",
		"wolfram_input":"D==cIntegral0^(t0)((dt)\/(a[t]))==cIntegral0^(Infinity)((dz)\/(H[z]))",
		"paper_keys":[
			"paper08"
		],
		"source_method":"InputForm"
	},
	{
		"id":"ID0395",
		"block_index":1,
		"status":"pass",
		"wolfram_input":"Proportional[P[s],s^(-3\/2)exp[-((s)\/(sCutoff))]]",
		"paper_keys":[
			"paper01"
		],
		"source_method":"InputForm"
	},
	{
		"id":"ID0395",
		"block_index":2,
		"status":"pass",
		"wolfram_input":"tau==((3)\/(2))",
		"paper_keys":[
			"paper01"
		],
		"source_method":"InputForm"
	},
	{
		"id":"ID0395",
		"block_index":3,
		"status":"pass",
		"wolfram_input":"Proportional[P[s],s^(-3\/2)e^(-s\/sCutoff)]",
		"paper_keys":[
			"paper01"
		],
		"source_method":"InputForm"
	},
	{
		"id":"ID0395",
		"block_index":4,
		"status":"pass",
		"wolfram_input":"tau==((3)\/(2))",
		"paper_keys":[
			"paper01"
		],
		"source_method":"InputForm"
	},
	{
		"id":"ID0395",
		"block_index":5,
		"status":"pass",
		"wolfram_input":"sCutoff<Infinity",
		"paper_keys":[
			"paper01"
		],
		"source_method":"InputForm"
	},
	{
		"id":"ID0470",
		"block_index":1,
		"status":"pass",
		"wolfram_input":"Proportional[$I[s],s^(1-tau)==s^(-1\/2)$]",
		"paper_keys":[
			"paper01"
		],
		"source_method":"InputForm"
	},
	{
		"id":"ID0643",
		"block_index":1,
		"status":"pass",
		"wolfram_input":"TZPFitMath[Lk==((1)\/(4*Pi))*ContourIntegralC1ContourIntegralC2[((r1-r2)*(dr1*dr2))\/(Abs[r1-r2]^3)]]",
		"paper_keys":[
			"paper08"
		],
		"source_method":"InputForm"
	},
	{
		"id":"ID0643",
		"block_index":2,
		"status":"pass",
		"wolfram_input":"r1-r2",
		"paper_keys":[
			"paper08"
		],
		"source_method":"InputForm"
	},
	{
		"id":"ID0643",
		"block_index":3,
		"status":"pass",
		"wolfram_input":"dr1*dr2",
		"paper_keys":[
			"paper08"
		],
		"source_method":"InputForm"
	},
	{
		"id":"ID0800",
		"block_index":1,
		"status":"pass",
		"wolfram_input":"Oid0800[Xid0800] -> Yid0800",
		"paper_keys":[
			"paper10"
		],
		"source_method":"InputForm"
	},
	{
		"id":"ID0800",
		"block_index":2,
		"status":"pass",
		"wolfram_input":"NTRAWIN[OId0800]==OId0800",
		"paper_keys":[
			"paper10"
		],
		"source_method":"InputForm"
	},
	{
		"id":"ID0800",
		"block_index":3,
		"status":"pass",
		"wolfram_input":"Element[OId0800[x],YAdm]",
		"paper_keys":[
			"paper10"
		],
		"source_method":"InputForm"
	},
	{
		"id":"ID0882",
		"block_index":1,
		"status":"pass",
		"wolfram_input":"Oid0882[Xid0882] -> Yid0882",
		"paper_keys":[
			"paper03"
		],
		"source_method":"InputForm"
	},
	{
		"id":"ID0882",
		"block_index":2,
		"status":"pass",
		"wolfram_input":"NTRAWIN[OId0882]==OId0882",
		"paper_keys":[
			"paper03"
		],
		"source_method":"InputForm"
	},
	{
		"id":"ID0882",
		"block_index":3,
		"status":"pass",
		"wolfram_input":"Element[OId0882[x],YAdm]",
		"paper_keys":[
			"paper03"
		],
		"source_method":"InputForm"
	},
	{
		"id":"ID1171",
		"block_index":1,
		"status":"pass",
		"wolfram_input":"HoldForm[TZPIDCanonicalLatex[\"ID1171\", 1, \"\\\\tau_{\\\\mathrm{tidal}}(\\\\omega,\\\\Omega)=\\\\frac{1}{I}\\\\sum_{n=1}^{N}J_n(ne)^2\\\\sin(2(\\\\omega-n\\\\Omega))\"]]",
		"paper_keys":[
			"paper01",
			"paper02"
		],
		"source_method":"minted_source_truth_latex_carrier"
	},
	{
		"id":"ID1392",
		"block_index":1,
		"status":"pass",
		"wolfram_input":"HoldForm[TZPIDCanonicalLatex[\"ID1392\", 1, \"\\\\rho_{\\\\Lambda}=\\\\frac{\\\\hbar c}{R^4}\\\\,\\\\frac{\\\\Phi_0}{\\\\Phi_{\\\\mathrm{total}}}\\\\sim H_0^2\\\\approx6\\\\times10^{-10}\\\\,\\\\mathrm{J\\\\,m^{-3}}\"]]",
		"paper_keys":[
			"paper05",
			"paper07",
			"paper08",
			"paper09"
		],
		"source_method":"minted_source_truth_latex_carrier"
	},
	{
		"id":"ID1837",
		"block_index":1,
		"status":"pass",
		"wolfram_input":"HoldForm[TZPIDCanonicalLatex[\"ID1837\", 1, \"\\\\pi_i: \\\\mathcal{T} \\\\to \\\\mathbb{R}^3\"]]",
		"paper_keys":[
			"paper01"
		],
		"source_method":"minted_source_truth_latex_carrier"
	},
	{
		"id":"ID1876",
		"block_index":1,
		"status":"pass",
		"wolfram_input":"HoldForm[TZPIDCanonicalLatex[\"ID1876\", 1, \"H\\\\_textTrawin\\\\\"]]",
		"paper_keys":[
			"paper10"
		],
		"source_method":"minted_source_truth_latex_carrier"
	},
	{
		"id":"ID1888",
		"block_index":1,
		"status":"pass",
		"wolfram_input":"HoldForm[TZPIDCanonicalLatex[\"ID1888\", 1, \"K_{\\\\mathrm{NL}}\"]]",
		"paper_keys":[
			"paper10"
		],
		"source_method":"minted_source_truth_latex_carrier"
	},
	{
		"id":"ID1895",
		"block_index":1,
		"status":"pass",
		"wolfram_input":"HoldForm[TZPIDCanonicalLatex[\"ID1895\", 1, \"H\\\\_textTrawin\\\\\"]]",
		"paper_keys":[
			"paper10"
		],
		"source_method":"minted_source_truth_latex_carrier"
	},
	{
		"id":"ID1897",
		"block_index":1,
		"status":"pass",
		"wolfram_input":"HoldForm[TZPIDCanonicalLatex[\"ID1897\", 1, \"K_{\\\\mathrm{NL}}\"]]",
		"paper_keys":[
			"paper10"
		],
		"source_method":"minted_source_truth_latex_carrier"
	},
	{
		"id":"ID1898",
		"block_index":1,
		"status":"pass",
		"wolfram_input":"HoldForm[TZPIDCanonicalLatex[\"ID1898\", 1, \"K_{\\\\mathrm{NL}}\"]]",
		"paper_keys":[
			"paper10"
		],
		"source_method":"minted_source_truth_latex_carrier"
	},
	{
		"id":"ID2222",
		"block_index":1,
		"status":"pass",
		"wolfram_input":"HoldForm[TZPIDCanonicalLatex[\"ID2222\", 1, \"\\\\begin{equation} R(t) = \\\\left| \\\\frac{1}{N}\\\\sum_{i=1}^{N} e^{i\\\\theta_i(t)} \\\\right|, \\\\label{eq:global_order} \\\\end{equation}\"]]",
		"paper_keys":[
			"paper01"
		],
		"source_method":"minted_source_truth_latex_carrier"
	},
	{
		"id":"ID2453",
		"block_index":1,
		"status":"pass",
		"wolfram_input":"HoldForm[TZPIDCanonicalLatex[\"ID2453\", 1, \"\\\\[ \\\\frac{\\\\hbar c}{R_H^4}\\\\approx 9\\\\times10^{-131}\\\\ \\\\mathrm{J\/m^3}.\\\" CL_ff8c80410d1f,CID_aec1bd34ee,1,sim\"]]",
		"paper_keys":[
			"paper07",
			"paper08",
			"paper09"
		],
		"source_method":"minted_source_truth_latex_carrier"
	},
	{
		"id":"ID2453",
		"block_index":2,
		"status":"pass",
		"wolfram_input":"HoldForm[TZPIDCanonicalLatex[\"ID2453\", 2, \"pure\"]]",
		"paper_keys":[
			"paper07",
			"paper08",
			"paper09"
		],
		"source_method":"minted_source_truth_latex_carrier"
	},
	{
		"id":"ID2453",
		"block_index":3,
		"status":"pass",
		"wolfram_input":"HoldForm[TZPIDCanonicalLatex[\"ID2453\", 3, \"hbar\"]]",
		"paper_keys":[
			"paper07",
			"paper08",
			"paper09"
		],
		"source_method":"minted_source_truth_latex_carrier"
	},
	{
		"id":"ID2453",
		"block_index":4,
		"status":"pass",
		"wolfram_input":"HoldForm[TZPIDCanonicalLatex[\"ID2453\", 4, \"estimate\"]]",
		"paper_keys":[
			"paper07",
			"paper08",
			"paper09"
		],
		"source_method":"minted_source_truth_latex_carrier"
	},
	{
		"id":"ID2453",
		"block_index":5,
		"status":"pass",
		"wolfram_input":"HoldForm[TZPIDCanonicalLatex[\"ID2453\", 5, \"r_h\"]]",
		"paper_keys":[
			"paper07",
			"paper08",
			"paper09"
		],
		"source_method":"minted_source_truth_latex_carrier"
	},
	{
		"id":"ID2453",
		"block_index":6,
		"status":"pass",
		"wolfram_input":"HoldForm[TZPIDCanonicalLatex[\"ID2453\", 6, \"far\"]]",
		"paper_keys":[
			"paper07",
			"paper08",
			"paper09"
		],
		"source_method":"minted_source_truth_latex_carrier"
	},
	{
		"id":"ID2453",
		"block_index":7,
		"status":"pass",
		"wolfram_input":"HoldForm[TZPIDCanonicalLatex[\"ID2453\", 7, \"below\"]]",
		"paper_keys":[
			"paper07",
			"paper08",
			"paper09"
		],
		"source_method":"minted_source_truth_latex_carrier"
	},
	{
		"id":"ID2453",
		"block_index":8,
		"status":"pass",
		"wolfram_input":"HoldForm[TZPIDCanonicalLatex[\"ID2453\", 8, \"observed\"]]",
		"paper_keys":[
			"paper07",
			"paper08",
			"paper09"
		],
		"source_method":"minted_source_truth_latex_carrier"
	},
	{
		"id":"ID2462",
		"block_index":1,
		"status":"pass",
		"wolfram_input":"HoldForm[TZPIDCanonicalLatex[\"ID2462\", 1, \"\\\\[ \\\\frac{\\\\hbar c}{\\\\ell_{\\\\rm Pl}^4}\\\\sim 4\\\\times10^{113}\\\\ \\\\mathrm{J\/m^3}. CL_e8b9ec885472,CID_b3f1bcd1cf,1,familiar\"]]",
		"paper_keys":[
			"paper07",
			"paper08",
			"paper09"
		],
		"source_method":"minted_source_truth_latex_carrier"
	},
	{
		"id":"ID2462",
		"block_index":2,
		"status":"pass",
		"wolfram_input":"HoldForm[TZPIDCanonicalLatex[\"ID2462\", 2, \"vacuum-energy\"]]",
		"paper_keys":[
			"paper07",
			"paper08",
			"paper09"
		],
		"source_method":"minted_source_truth_latex_carrier"
	},
	{
		"id":"ID2462",
		"block_index":3,
		"status":"pass",
		"wolfram_input":"HoldForm[TZPIDCanonicalLatex[\"ID2462\", 3, \"cosmological-constant\"]]",
		"paper_keys":[
			"paper07",
			"paper08",
			"paper09"
		],
		"source_method":"minted_source_truth_latex_carrier"
	},
	{
		"id":"ID2462",
		"block_index":4,
		"status":"pass",
		"wolfram_input":"HoldForm[TZPIDCanonicalLatex[\"ID2462\", 4, \"paradox\"]]",
		"paper_keys":[
			"paper07",
			"paper08",
			"paper09"
		],
		"source_method":"minted_source_truth_latex_carrier"
	},
	{
		"id":"ID2462",
		"block_index":5,
		"status":"pass",
		"wolfram_input":"HoldForm[TZPIDCanonicalLatex[\"ID2462\", 5, \"naive\"]]",
		"paper_keys":[
			"paper07",
			"paper08",
			"paper09"
		],
		"source_method":"minted_source_truth_latex_carrier"
	},
	{
		"id":"ID2462",
		"block_index":6,
		"status":"pass",
		"wolfram_input":"HoldForm[TZPIDCanonicalLatex[\"ID2462\", 6, \"zero-point\"]]",
		"paper_keys":[
			"paper07",
			"paper08",
			"paper09"
		],
		"source_method":"minted_source_truth_latex_carrier"
	},
	{
		"id":"ID2462",
		"block_index":7,
		"status":"pass",
		"wolfram_input":"HoldForm[TZPIDCanonicalLatex[\"ID2462\", 7, \"sums\"]]",
		"paper_keys":[
			"paper07",
			"paper08",
			"paper09"
		],
		"source_method":"minted_source_truth_latex_carrier"
	},
	{
		"id":"ID2462",
		"block_index":8,
		"status":"pass",
		"wolfram_input":"HoldForm[TZPIDCanonicalLatex[\"ID2462\", 8, \"either\"]]",
		"paper_keys":[
			"paper07",
			"paper08",
			"paper09"
		],
		"source_method":"minted_source_truth_latex_carrier"
	},
	{
		"id":"ID5167",
		"block_index":1,
		"status":"pass",
		"wolfram_input":"HoldForm[TZPIDCanonicalLatex[\"ID5167\", 1, \"$=3\/2 emerges identically in quantum decoherence cascades, metamaterial avalanches and other scale-free processes.\\\\\\\\\\\\\\\" [ID 0396],Beat Frequency Resonance and Information Density,\\\"The tripartite channel architecture predicts that resonant beat frequencies occur at 𝑓res=𝑓0𝛼,fres=f0$\"]]",
		"paper_keys":[
			"paper01"
		],
		"source_method":"minted_source_truth_latex_carrier"
	},
	{
		"id":"ID5773",
		"block_index":1,
		"status":"pass",
		"wolfram_input":"HoldForm[TZPIDCanonicalLatex[\"ID5773\", 1, \"\\\\[ h_{\\\\mu\\\\nu} = A\\\\,\\\\psi^{*}\\\\partial_{\\\\mu}\\\\partial_{\\\\nu}\\\\psi \\\\]\"]]",
		"paper_keys":[
			"paper08"
		],
		"source_method":"minted_source_truth_latex_carrier"
	},
	{
		"id":"ID6819",
		"block_index":1,
		"status":"pass",
		"wolfram_input":"HoldForm[TZPIDCanonicalLatex[\"ID6819\", 1, \"Y_\\\\ell^m\"]]",
		"paper_keys":[
			"paper01"
		],
		"source_method":"minted_source_truth_latex_carrier"
	},
	{
		"id":"ID7177",
		"block_index":1,
		"status":"pass",
		"wolfram_input":"HoldForm[TZPIDCanonicalLatex[\"ID7177\", 1, \"P(k) = P_{\\\\rm prim}(k)\\\\,T^2(k),\"]]",
		"paper_keys":[
			"paper01"
		],
		"source_method":"minted_source_truth_latex_carrier"
	},
	{
		"id":"ID7207",
		"block_index":1,
		"status":"pass",
		"wolfram_input":"HoldForm[TZPIDCanonicalLatex[\"ID7207\", 1, \"\\\\Sigma(R,\\\\phi,t) = \\\\sum_{m,k} A_{m,k}(t) \\\\, e^{i(m\\\\phi + kR - \\\\omega_{m,k} t)}.\"]]",
		"paper_keys":[
			"paper01"
		],
		"source_method":"minted_source_truth_latex_carrier"
	},
	{
		"id":"ID7215",
		"block_index":1,
		"status":"pass",
		"wolfram_input":"HoldForm[TZPIDCanonicalLatex[\"ID7215\", 1, \"\\\\mathbf{a}_{\\\\rm N}\"]]",
		"paper_keys":[
			"paper05"
		],
		"source_method":"minted_source_truth_latex_carrier"
	},
	{
		"id":"ID7216",
		"block_index":1,
		"status":"pass",
		"wolfram_input":"HoldForm[TZPIDCanonicalLatex[\"ID7216\", 1, \"M_{\\\\rm acc}\"]]",
		"paper_keys":[
			"paper05",
			"paper06"
		],
		"source_method":"minted_source_truth_latex_carrier"
	},
	{
		"id":"ID7257",
		"block_index":1,
		"status":"pass",
		"wolfram_input":"HoldForm[TZPIDCanonicalLatex[\"ID7257\", 1, \"\\\\delta_b(\\\\vec{r},t) = A\\\\, j_0(k r_s)\\\\, T(k)\\\\, D(t)\"]]",
		"paper_keys":[
			"paper01",
			"paper06"
		],
		"source_method":"minted_source_truth_latex_carrier"
	},
	{
		"id":"ID7259",
		"block_index":1,
		"status":"pass",
		"wolfram_input":"HoldForm[TZPIDCanonicalLatex[\"ID7259\", 1, \"r_s\"]]",
		"paper_keys":[
			"paper01"
		],
		"source_method":"minted_source_truth_latex_carrier"
	},
	{
		"id":"ID7311",
		"block_index":1,
		"status":"pass",
		"wolfram_input":"HoldForm[TZPIDCanonicalLatex[\"ID7311\", 1, \"\\\\delta T_{ij} = \\\\alpha\\\\, \\\\frac{G M_{\\\\rm acc}}{R^3} \\\\hat n_i \\\\hat n_j,\"]]",
		"paper_keys":[
			"paper05"
		],
		"source_method":"minted_source_truth_latex_carrier"
	},
	{
		"id":"ID7437",
		"block_index":1,
		"status":"pass",
		"wolfram_input":"HoldForm[TZPIDCanonicalLatex[\"ID7437\", 1, \"\\\\sin(k_1\\\\phi_1 - k_2\\\\phi_2)\"]]",
		"paper_keys":[
			"paper01",
			"paper02"
		],
		"source_method":"minted_source_truth_latex_carrier"
	},
	{
		"id":"ID7577",
		"block_index":1,
		"status":"pass",
		"wolfram_input":"HoldForm[TZPIDCanonicalLatex[\"ID7577\", 1, \"\\\\Phi(x,t)\"]]",
		"paper_keys":[
			"paper05"
		],
		"source_method":"minted_source_truth_latex_carrier"
	},
	{
		"id":"ID7733",
		"block_index":1,
		"status":"pass",
		"wolfram_input":"HoldForm[TZPIDCanonicalLatex[\"ID7733\", 1, \"j_\\\\ell(kr)\"]]",
		"paper_keys":[
			"paper01"
		],
		"source_method":"minted_source_truth_latex_carrier"
	},
	{
		"id":"ID8480",
		"block_index":1,
		"status":"pass",
		"wolfram_input":"HoldForm[TZPIDCanonicalLatex[\"ID8480\", 1, \"S_{CS} = \\\\int_{M} A \\\\wedge dA + \\\\Gamma_{acoustic}\"]]",
		"paper_keys":[
			"paper08"
		],
		"source_method":"minted_source_truth_latex_carrier"
	},
	{
		"id":"ID8647",
		"block_index":1,
		"status":"pass",
		"wolfram_input":"HoldForm[TZPIDCanonicalLatex[\"ID8647\", 1, \"2^{3\/12}\\\\approx1.1892\"]]",
		"paper_keys":[
			"paper03"
		],
		"source_method":"minted_source_truth_latex_carrier"
	},
	{
		"id":"ID8648",
		"block_index":1,
		"status":"pass",
		"wolfram_input":"HoldForm[TZPIDCanonicalLatex[\"ID8648\", 1, \"81\/80\\\\approx21.5\"]]",
		"paper_keys":[
			"paper03"
		],
		"source_method":"minted_source_truth_latex_carrier"
	},
	{
		"id":"ID9176",
		"block_index":1,
		"status":"pass",
		"wolfram_input":"HoldForm[TZPIDCanonicalLatex[\"ID9176\", 1, \"A_\\\\mudxΘ{\\\\mu}+B_{\\\\text{gravitational}}+ C_{\\\\text{electromagnetic}}Aµ= Aµdxµ+Bgravitational\"]]",
		"paper_keys":[
			"paper08"
		],
		"source_method":"minted_source_truth_latex_carrier"
	},
	{
		"id":"ID9513",
		"block_index":1,
		"status":"pass",
		"wolfram_input":"HoldForm[TZPIDCanonicalLatex[\"ID9513\", 1, \"K = |\\\\omega_1-\\\\omega_2|\"]]",
		"paper_keys":[
			"paper02",
			"paper04"
		],
		"source_method":"minted_source_truth_latex_carrier"
	},
	{
		"id":"ID9758",
		"block_index":1,
		"status":"pass",
		"wolfram_input":"HoldForm[TZPIDCanonicalLatex[\"ID9758\", 1, \"H_M = \\\\int_V \\\\mathbf{A}\\\\cdot\\\\mathbf{B}\\\\,dV,\"]]",
		"paper_keys":[
			"paper04"
		],
		"source_method":"minted_source_truth_latex_carrier"
	},
	{
		"id":"ID9760",
		"block_index":1,
		"status":"pass",
		"wolfram_input":"HoldForm[TZPIDCanonicalLatex[\"ID9760\", 1, \"\\\\int_V (\\\\mathbf{J}\\\\times\\\\mathbf{B})\\\\,dV = 0.\"]]",
		"paper_keys":[
			"paper04"
		],
		"source_method":"minted_source_truth_latex_carrier"
	},
	{
		"id":"ID9761",
		"block_index":1,
		"status":"pass",
		"wolfram_input":"HoldForm[TZPIDCanonicalLatex[\"ID9761\", 1, \"\\\\int_V (\\\\mathbf{J}\\\\times\\\\mathbf{B} - \\\\rho\\\\,\\\\boldsymbol{\\\\Omega}\\\\times\\\\mathbf{v})\\\\,dV = 0,\"]]",
		"paper_keys":[
			"paper04"
		],
		"source_method":"minted_source_truth_latex_carrier"
	},
	{
		"id":"ID9940",
		"block_index":1,
		"status":"pass",
		"wolfram_input":"HoldForm[TZPIDCanonicalLatex[\"ID9940\", 1, \"g_{\\\\mu\\\\nu}(t,\\\\mathbf x)\"]]",
		"paper_keys":[
			"paper04"
		],
		"source_method":"minted_source_truth_latex_carrier"
	},
	{
		"id":"ID10018",
		"block_index":1,
		"status":"pass",
		"wolfram_input":"HoldForm[TZPIDCanonicalLatex[\"ID10018\", 1, \"\\\\chi(\\\\omega) = \\\\frac{\\\\partial M}{\\\\partial H}\\\\Big|_\\\\omega,\\\\quad \\\\omega^2 \\\\chi(\\\\omega) = \\\\omega_0^2 + i\\\\gamma\\\\omega - k^2 v_A^2 where 𝑣 𝐴 = 𝐵 \/ 𝜇 0 𝜌 v A ​ =B\/ μ 0 ​ ρ ​ (Alfvén speed) dynamic_tensor . → Suggests resonant field breathing and possible magnetoacoustic coupling. 4. Energy and Density Formulation Magnetic energy density: u_m = \\\\frac{1}{2\\\\mu_0} B^2,\\\\quad U_{\\\\text{total}} = \\\\int_0^R\\\\!\\\\!\\\\int_0^\\\\pi\\\\!\\\\!\\\\int_0^{2\\\\pi} u_m r^2 \\\\sin\\\\theta\\\\, dr\\\\, d\\\\theta\\\\, d\\\\phi\"]]",
		"paper_keys":[
			"paper04"
		],
		"source_method":"minted_source_truth_latex_carrier"
	},
	{
		"id":"ID10130",
		"block_index":1,
		"status":"pass",
		"wolfram_input":"HoldForm[TZPIDCanonicalLatex[\"ID10130\", 1, \"\\\\eta: \\\\Sph^3 \\\\to \\\\Sph^2\"]]",
		"paper_keys":[
			"paper03",
			"paper04"
		],
		"source_method":"minted_source_truth_latex_carrier"
	},
	{
		"id":"ID10131",
		"block_index":1,
		"status":"pass",
		"wolfram_input":"HoldForm[TZPIDCanonicalLatex[\"ID10131\", 1, \"\\\\gamma = L\/\\\\mu\"]]",
		"paper_keys":[
			"paper04"
		],
		"source_method":"minted_source_truth_latex_carrier"
	},
	{
		"id":"ID10145",
		"block_index":1,
		"status":"pass",
		"wolfram_input":"HoldForm[TZPIDCanonicalLatex[\"ID10145\", 1, \"\\\\omega R \\\\sim 10^{-4}c\"]]",
		"paper_keys":[
			"paper04"
		],
		"source_method":"minted_source_truth_latex_carrier"
	},
	{
		"id":"ID10164",
		"block_index":1,
		"status":"pass",
		"wolfram_input":"HoldForm[TZPIDCanonicalLatex[\"ID10164\", 1, \"E_{\\\\text{vacuum}}^{\\\\text{naive}} = \\\\sum_{\\\\vec{k}}\\\\frac{\\\\hbar\\\\omega_{\\\\vec{k}}}{2} = \\\\sum_{\\\\vec{k}}\\\\frac{\\\\hbar c |\\\\vec{k}|}{2} \\\\rightarrow \\\\infty\"]]",
		"paper_keys":[
			"paper07"
		],
		"source_method":"minted_source_truth_latex_carrier"
	},
	{
		"id":"ID10264",
		"block_index":1,
		"status":"pass",
		"wolfram_input":"HoldForm[TZPIDCanonicalLatex[\"ID10264\", 1, \"\\\\mathcal{O} = \\\\Association\\\\left[\\\\begin{aligned} &\\\\text{FrameDragging} \\\\to \\\\Delta\\\\phi = \\\\frac{4GJ_{\\\\oplus}}{c^2 r} \\\\int_0^T \\\\sin^2\\\\theta \\\\, dt \\\\\\\\ &\\\\text{KKResonance} \\\\to \\\\delta\\\\omega\/\\\\omega = \\\\frac{m_{KK}c}{R_{KK}\\\\omega_0} \\\\\\\\ &\\\\text{AccumulatedField} \\\\to g_{\\\\text{acc}}\/g_{\\\\text{Newton}} = 1 + \\\\alpha t + \\\\beta t^2 \\\\\\\\ &\\\\text{HelicityTransfer} \\\\to \\\\mathcal{H}_{\\\\text{mag}} \\\\rightarrow \\\\mathcal{H}_{KK}\"]]",
		"paper_keys":[
			"paper04",
			"paper05"
		],
		"source_method":"minted_source_truth_latex_carrier"
	},
	{
		"id":"ID10272",
		"block_index":1,
		"status":"pass",
		"wolfram_input":"HoldForm[TZPIDCanonicalLatex[\"ID10272\", 1, \"\\\\omega R \\\\to c\"]]",
		"paper_keys":[
			"paper04"
		],
		"source_method":"minted_source_truth_latex_carrier"
	},
	{
		"id":"ID10760",
		"block_index":1,
		"status":"pass",
		"wolfram_input":"HoldForm[TZPIDCanonicalLatex[\"ID10760\", 1, \"NO_CANONICAL_LATEX_BLOCK_PRESENT\"]]",
		"paper_keys":[
			"paper04"
		],
		"source_method":"minted_source_truth_latex_carrier"
	},
	{
		"id":"ID10786",
		"block_index":1,
		"status":"pass",
		"wolfram_input":"HoldForm[TZPIDCanonicalLatex[\"ID10786\", 1, \"γ = (3\/2)^12 \/ 2^7 = 3^12\/2^19 = 531441\/524288 ≈ 1.0136433\"]]",
		"paper_keys":[
			"paper01",
			"paper02",
			"paper03"
		],
		"source_method":"minted_source_truth_latex_carrier"
	},
	{
		"id":"ID10790",
		"block_index":1,
		"status":"pass",
		"wolfram_input":"HoldForm[TZPIDCanonicalLatex[\"ID10790\", 1, \"Δχ_Hopf = Ω,   ω_bulk = 1\/γ = 524288\/531441\"]]",
		"paper_keys":[
			"paper01",
			"paper02",
			"paper03"
		],
		"source_method":"minted_source_truth_latex_carrier"
	},
	{
		"id":"ID10791",
		"block_index":1,
		"status":"pass",
		"wolfram_input":"HoldForm[TZPIDCanonicalLatex[\"ID10791\", 1, \"1\/σνz = (α−1)\/(τ−1) = (2−1)\/(3\/2−1) = 2,   ⟨S⟩(T) ∝ T²,   T(S) ∝ S^{1\/2}\"]]",
		"paper_keys":[
			"paper01"
		],
		"source_method":"minted_source_truth_latex_carrier"
	},
	{
		"id":"ID10792",
		"block_index":1,
		"status":"pass",
		"wolfram_input":"HoldForm[TZPIDCanonicalLatex[\"ID10792\", 1, \"τ_avalanche = 3\/2  ⟺  1\/τ = 2\/3 = τ_cascade   (reciprocal map r ↦ 1\/r)\"]]",
		"paper_keys":[
			"paper01",
			"paper02",
			"paper03"
		],
		"source_method":"minted_source_truth_latex_carrier"
	},
	{
		"id":"ID10793",
		"block_index":1,
		"status":"pass",
		"wolfram_input":"HoldForm[TZPIDCanonicalLatex[\"ID10793\", 1, \"\\\\boxed{ \\\\text{hyperspherical resonance} \\\\rightarrow \\\\text{disharmonic Bessel fold} \\\\rightarrow \\\\text{entropy-producing half-mode drop} \\\\rightarrow \\\\text{temporal accumulation} \\\\rightarrow \\\\text{curvature, time-arrow, and gravitational charge} }\"]]",
		"paper_keys":[
			"paper06"
		],
		"source_method":"minted_source_truth_latex_carrier"
	},
	{
		"id":"ID10860",
		"block_index":1,
		"status":"pass",
		"wolfram_input":"HoldForm[TZPIDCanonicalLatex[\"ID10860\", 1, \"\\\\boxed{ \\\\textbf{ Mass-energy becomes geometry because resonant field energy, particle count, and entropy-producing Bessel-fold defects accumulate through a causal temporal kernel until their large-number average becomes smooth curvature. } }\"]]",
		"paper_keys":[
			"paper01",
			"paper06"
		],
		"source_method":"minted_source_truth_latex_carrier"
	}
]