{
  "tzpid": "ID4947",
  "title": "Capacitance Relation",
  "uuid": "fc47023c-00c3-5a68-9b4c-3d7619e8e0d7",
  "PiID": "9397805419341",
  "RTEID": "RTE:P19210.2996:T0.2367",
  "TZPi": "5",
  "PiPE_position": "4954",
  "poloidal_theta_rad": "19210.2996",
  "toroidal_phi_rad": "0.2367",
  "loc_class": "QA - Mathematics: geometry and topology",
  "arxiv_class": "math.DG",
  "creator": "Daniel Alexander Trawin",
  "creator_orcid": "https://orcid.org/0009-0001-4630-3715",
  "embedded_at_utc": "2026-06-10T00:41:53+00:00"
}
