{
  "tzpid": "ID6457",
  "title": "Practical Next Steps I Can Execute Now (Pick Any or Several): R(φ,θ)",
  "uuid": "08f3b66a-457d-5634-a088-82db6938b7d5",
  "PiID": "3041377655279",
  "RTEID": "RTE:P25073.9650:T3.6151",
  "TZPi": "7",
  "PiPE_position": "6464",
  "poloidal_theta_rad": "25073.9650",
  "toroidal_phi_rad": "3.6151",
  "loc_class": "",
  "arxiv_class": "",
  "creator": "Daniel Alexander Trawin",
  "creator_orcid": "https://orcid.org/0009-0001-4630-3715",
  "embedded_at_utc": "2026-06-10T00:41:57+00:00"
}
