{
  "tzpid": "ID5670",
  "title": "Phase Angle Expansion",
  "uuid": "e2c04382-d992-555b-bdfe-da64f6d3c802",
  "PiID": "7213444730605",
  "RTEID": "RTE:P22017.8692:T4.8628",
  "TZPi": "4",
  "PiPE_position": "5677",
  "poloidal_theta_rad": "22017.8692",
  "toroidal_phi_rad": "4.8628",
  "loc_class": "QC - Physics",
  "arxiv_class": "physics.gen-ph",
  "creator": "Daniel Alexander Trawin",
  "creator_orcid": "https://orcid.org/0009-0001-4630-3715",
  "embedded_at_utc": "2026-06-10T00:41:55+00:00"
}
