{
  "tzpid": "ID3484",
  "title": "Density Evolution Equation",
  "uuid": "abff8584-d87d-5fef-8c4e-a0e451132488",
  "PiID": "5103346711031",
  "RTEID": "RTE:P13529.1457:T3.4423",
  "TZPi": "6",
  "PiPE_position": "3491",
  "poloidal_theta_rad": "13529.1457",
  "toroidal_phi_rad": "3.4423",
  "loc_class": "QC - Physics",
  "arxiv_class": "physics.gen-ph",
  "creator": "Daniel Alexander Trawin",
  "creator_orcid": "https://orcid.org/0009-0001-4630-3715",
  "embedded_at_utc": "2026-06-10T00:41:49+00:00"
}
