{
  "tzpid": "ID7736",
  "title": "How This Ties into Your TZPQVS Superconducting Spherical Enclosure + Cymatics Id (2)",
  "uuid": "5b8b7567-4960-5584-bd7a-bf7f17d3f1e8",
  "PiID": "5420516184163",
  "RTEID": "RTE:P30040.6060:T5.5154",
  "TZPi": "6",
  "PiPE_position": "7743",
  "poloidal_theta_rad": "30040.6060",
  "toroidal_phi_rad": "5.5154",
  "loc_class": "",
  "arxiv_class": "",
  "creator": "Daniel Alexander Trawin",
  "creator_orcid": "https://orcid.org/0009-0001-4630-3715",
  "embedded_at_utc": "2026-06-10T00:42:00+00:00"
}
